decentryk_qr/__init__.py
decentryk_qr/cli.py
decentryk_qr/qr_processor.py
decentryk_qr/tests/__init__.py
decentryk_qr/tests/test_qr_processor.py
decentryk_qr-0.2.1.dist-info/METADATA
decentryk_qr-0.2.1.dist-info/WHEEL
decentryk_qr-0.2.1.dist-info/entry_points.txt
decentryk_qr-0.2.1.dist-info/top_level.txt
decentryk_qr-0.2.1.dist-info/RECORD
