Metadata-Version: 2.1
Name: decentryk_qr
Version: 0.2.1
Summary: A package for combining and verifying QR codes using cryptographic hashes
Home-page: https://github.com/yourusername/decentryk_qr
Author: Zac Weigold
Author-email: zacweigold@gmail.com
Classifier: Programming Language :: Python :: 3
Classifier: License :: OSI Approved :: MIT License
Classifier: Operating System :: OS Independent
Classifier: Development Status :: 4 - Beta
Classifier: Intended Audience :: Developers
Requires-Python: >=3.6
Requires-Dist: click >=7.1.2
Requires-Dist: qrcode >=7.4.2
Requires-Dist: Pillow >=10.0.0
Requires-Dist: opencv-python >=4.8.0.74
Requires-Dist: numpy >=1.24.3
